LICENSE
MANIFEST.in
README.rst
requirements.txt
setup.py
bisheng/__init__.py
bisheng/jianfan.py
bisheng/s2t.txt
bisheng/spacing.py
bisheng/t2s.txt
bisheng.egg-info/PKG-INFO
bisheng.egg-info/SOURCES.txt
bisheng.egg-info/dependency_links.txt
bisheng.egg-info/requires.txt
bisheng.egg-info/top_level.txt