Metadata-Version: 1.1
Name: bisheng
Version: 0.10.0
Summary: A set of utility functions for processing Chinese text.
Home-page: https://github.com/eliangcs/bisheng
Author: Chang-Hung Liang
Author-email: eliang.cs@gmail.com
License: BSD
Platform: UNKNOWN
Classifier: Development Status :: 4 - Beta
Classifier: Environment :: Console
Classifier: Intended Audience :: Developers
Classifier: License :: OSI Approved :: BSD License
Classifier: Operating System :: OS Independent
Classifier: Programming Language :: Python
Classifier: Programming Language :: Python :: 2
Classifier: Programming Language :: Python :: 2.6
Classifier: Programming Language :: Python :: 2.7
Classifier: Topic :: Text Processing
Classifier: Topic :: Text Processing :: Filters
Classifier: Topic :: Software Development :: Libraries :: Python Modules
